colorr/__init__.py
colorr-1.0.3.dist-info/LICENSE
colorr-1.0.3.dist-info/METADATA
colorr-1.0.3.dist-info/WHEEL
colorr-1.0.3.dist-info/top_level.txt
colorr-1.0.3.dist-info/RECORD
