Metadata-Version: 2.1
Name: colorr
Version: 1.0.3
Summary: A tool for picking Colorrs
Home-page: https://github.com/ItzAfroBoy/colorr
Author: ItzAfroBoy
Author-email: spareafro@post.com
License: UNKNOWN
Platform: UNKNOWN
Classifier: Programming Language :: Python :: 3
Classifier: License :: OSI Approved :: MIT License
Classifier: Operating System :: OS Independent
Requires-Python: >=3.6
